dtfield/__init__.py
dtfield/_imports.py
dtfield/base_enum.py
dtfield/engine.py
dtfield/functions.py
dtfield/parse/__init__.py
dtfield/parse/_types.py
dtfield/parse/dates.py
dtfield/parse/json_encoder.py
dtfield/parse/null.py
dtfield/parse/number.py
dtfield/parse/string.py
dtfield/parse/type_hint.py
dtfield-0.2.3.dist-info/WHEEL
dtfield-0.2.3.dist-info/METADATA
dtfield-0.2.3.dist-info/RECORD
