Metadata-Version: 2.1
Name: dtfield
Version: 0.2.3
Summary: 
Author: Daniel Arantes
Author-email: arantesdv@me.com
Requires-Python: >=3.9,<4.0
Classifier: Programming Language :: Python :: 3
Classifier: Programming Language :: Python :: 3.10
Classifier: Programming Language :: Python :: 3.9
Requires-Dist: Jinja2 (>=3.1.2,<4.0.0)
Requires-Dist: Unidecode (>=1.3.6,<2.0.0)
Requires-Dist: anyio (>=3.7.0,<4.0.0)
Requires-Dist: dtbase (>=0.0.4,<0.0.5)
Requires-Dist: itsdangerous (>=2.1.2,<3.0.0)
Requires-Dist: python-multipart (>=0.0.6,<0.0.7)
Requires-Dist: typing-extensions (>=4.6.3,<5.0.0)
Requires-Dist: uvicorn (>=0.22.0,<0.23.0)
